MANIFEST.in
README.rst
setup.py
lekt_mfe.egg-info/PKG-INFO
lekt_mfe.egg-info/SOURCES.txt
lekt_mfe.egg-info/dependency_links.txt
lekt_mfe.egg-info/entry_points.txt
lekt_mfe.egg-info/requires.txt
lekt_mfe.egg-info/top_level.txt
lektmfe/__about__.py
lektmfe/__init__.py
lektmfe/plugin.py
lektmfe/patches/.gitignore
lektmfe/patches/caddyfile
lektmfe/patches/k8s-deployments
lektmfe/patches/k8s-services
lektmfe/patches/local-docker-compose-dev-services
lektmfe/patches/local-docker-compose-prod-services
lektmfe/patches/openedx-lms-common-settings
lektmfe/patches/openedx-lms-development-settings
lektmfe/patches/openedx-lms-production-settings
lektmfe/templates/mfe/apps/.gitignore
lektmfe/templates/mfe/apps/mfe/webpack.dev-tutor.config.js
lektmfe/templates/mfe/build/.gitignore
lektmfe/templates/mfe/build/mfe/Caddyfile
lektmfe/templates/mfe/build/mfe/Dockerfile
lektmfe/templates/mfe/build/mfe/env/development
lektmfe/templates/mfe/build/mfe/env/production
lektmfe/templates/mfe/build/mfe/i18n/i18n-merge.js
lektmfe/templates/mfe/tasks/.gitignore
lektmfe/templates/mfe/tasks/lms/init