Metadata-Version: 2.1
Name: lekt-mfe
Version: 14.0.33
Summary: mfe plugin for Lekt
Home-page: https://github.com/lektorium-tutor/lekt-mfe
Author: Overhang.IO
Maintainer: tCRIL
Maintainer-email: adolfo@tcril.org
License: AGPLv3
Project-URL: Code, https://github.com/lektorium-tutor/lekt-mfe
Classifier: Development Status :: 3 - Alpha
Classifier: Intended Audience :: Developers
Classifier: License :: OSI Approved :: GNU Affero General Public License v3
Classifier: Operating System :: OS Independent
Classifier: Programming Language :: Python
Classifier: Programming Language :: Python :: 3.5
Classifier: Programming Language :: Python :: 3.6
Classifier: Programming Language :: Python :: 3.7
Classifier: Programming Language :: Python :: 3.8
Classifier: Programming Language :: Python :: 3.9
Classifier: Programming Language :: Python :: 3.10
Requires-Python: >=3.5
